aviary/core.py
aviary/dataset_server.py
aviary/env.py
aviary/env_client.py
aviary/functional.py
aviary/main.py
aviary/message.py
aviary/py.typed
aviary/render.py
aviary/utils.py
aviary/version.py
aviary/tools/__init__.py
aviary/tools/argref.py
aviary/tools/base.py
aviary/tools/server.py
aviary/tools/utils.py
fhaviary-0.32.0.dist-info/licenses/LICENSE
fhaviary-0.32.0.dist-info/METADATA
fhaviary-0.32.0.dist-info/WHEEL
fhaviary-0.32.0.dist-info/entry_points.txt
fhaviary-0.32.0.dist-info/top_level.txt
fhaviary-0.32.0.dist-info/RECORD
