Metadata-Version: 2.4
Name: fhaviary
Version: 0.32.0
Summary: Gymnasium framework for training language model agents on constructive tasks
Author-email: FutureHouse technical staff <hello@futurehouse.org>
License:                                  Apache License
Project-URL: issues, https://github.com/Future-House/aviary/issues
Project-URL: repository, https://github.com/Future-House/aviary
Classifier: Intended Audience :: Developers
Classifier: License :: OSI Approved :: Apache Software License
Classifier: Operating System :: OS Independent
Classifier: Programming Language :: Python :: 3 :: Only
Classifier: Programming Language :: Python :: 3.11
Classifier: Programming Language :: Python :: 3.12
Classifier: Programming Language :: Python :: 3.13
Classifier: Programming Language :: Python :: 3.14
Classifier: Programming Language :: Python
Classifier: Topic :: Scientific/Engineering :: Artificial Intelligence
Requires-Python: >=3.11
License-File: LICENSE
Requires-Dist: docstring_parser>=0.16
Requires-Dist: httpx
Requires-Dist: httpx-aiohttp
Requires-Dist: pydantic~=2.0
Provides-Extra: cloud
Requires-Dist: boto3; extra == "cloud"
Provides-Extra: dev
Requires-Dist: aviary.gsm8k[typing]; extra == "dev"
Requires-Dist: aviary.hotpotqa; extra == "dev"
Requires-Dist: aviary.labbench[dev]; extra == "dev"
Requires-Dist: aviary.lfrqa[dev]; extra == "dev"
Requires-Dist: aviary.notebook[dev]; extra == "dev"
Requires-Dist: fhaviary[image,llm,server,typing,xml]; extra == "dev"
Requires-Dist: ipython>=8; extra == "dev"
Requires-Dist: jupyter>=1.0.0; extra == "dev"
Requires-Dist: litellm>=1.80.11; extra == "dev"
Requires-Dist: mypy>=1.19; extra == "dev"
Requires-Dist: numpy>=1; extra == "dev"
Requires-Dist: prek; extra == "dev"
Requires-Dist: pydantic~=2.9; extra == "dev"
Requires-Dist: pylint-pydantic; extra == "dev"
Requires-Dist: pylint>=4; extra == "dev"
Requires-Dist: pytest-asyncio; extra == "dev"
Requires-Dist: pytest-recording; extra == "dev"
Requires-Dist: pytest-rerunfailures; extra == "dev"
Requires-Dist: pytest-subtests; extra == "dev"
Requires-Dist: pytest-sugar; extra == "dev"
Requires-Dist: pytest-timer[colorama]; extra == "dev"
Requires-Dist: pytest-xdist; extra == "dev"
Requires-Dist: pytest>=8; extra == "dev"
Requires-Dist: refurb>=2; extra == "dev"
Requires-Dist: tenacity; extra == "dev"
Requires-Dist: typeguard; extra == "dev"
Requires-Dist: vcrpy>=8; extra == "dev"
Provides-Extra: gsm8k
Requires-Dist: aviary.gsm8k; extra == "gsm8k"
Provides-Extra: hotpotqa
Requires-Dist: aviary.hotpotqa; extra == "hotpotqa"
Provides-Extra: image
Requires-Dist: Pillow; extra == "image"
Provides-Extra: labbench
Requires-Dist: aviary.labbench; extra == "labbench"
Provides-Extra: lfrqa
Requires-Dist: aviary.lfrqa; extra == "lfrqa"
Provides-Extra: llm
Requires-Dist: fhlmi; extra == "llm"
Requires-Dist: litellm>=1.49.1; extra == "llm"
Requires-Dist: packaging; extra == "llm"
Provides-Extra: notebook
Requires-Dist: aviary.notebook; extra == "notebook"
Provides-Extra: server
Requires-Dist: click; extra == "server"
Requires-Dist: cloudpickle; extra == "server"
Requires-Dist: fastapi; extra == "server"
Requires-Dist: uvicorn; extra == "server"
Provides-Extra: typing
Requires-Dist: boto3-stubs[s3]; extra == "typing"
Requires-Dist: numpy; extra == "typing"
Requires-Dist: pandas-stubs; extra == "typing"
Requires-Dist: types-Pillow; extra == "typing"
Provides-Extra: xml
Requires-Dist: dicttoxml; extra == "xml"
Dynamic: license-file
